pytest_exact_fixtures/__init__.py
pytest_exact_fixtures-0.3.dist-info/LICENSE.txt
pytest_exact_fixtures-0.3.dist-info/METADATA
pytest_exact_fixtures-0.3.dist-info/WHEEL
pytest_exact_fixtures-0.3.dist-info/entry_points.txt
pytest_exact_fixtures-0.3.dist-info/top_level.txt
pytest_exact_fixtures-0.3.dist-info/RECORD
