Metadata-Version: 2.1
Name: pytest-exact-fixtures
Version: 0.3
Summary: Parse queries in Lucene and Elasticsearch syntaxes
Home-page: http://github.com/lrowe/pytest_exact_fixtures
Author: Laurence Rowe
Author-email: laurence@lrowe.co.uk
License: MIT
Platform: UNKNOWN
Classifier: Intended Audience :: Developers
Classifier: Programming Language :: Python
Classifier: Programming Language :: Python :: 2.7
Classifier: Programming Language :: Python :: 3
Classifier: Programming Language :: Python :: 3.3
Classifier: Programming Language :: Python :: 3.4
Classifier: Programming Language :: Python :: 3.5
Classifier: Programming Language :: Python :: 3.6
Classifier: Programming Language :: Python :: 3.7
Classifier: Programming Language :: Python :: Implementation :: CPython
Classifier: Programming Language :: Python :: Implementation :: PyPy
Classifier: License :: OSI Approved :: MIT License
Requires-Dist: pytest (>=3.3.0)
